yt_dlp_plugins/extractor/getpot_bgutil.py
yt_dlp_plugins/extractor/getpot_bgutil_http.py
yt_dlp_plugins/extractor/getpot_bgutil_script.py
bgutil_ytdlp_pot_provider-1.2.2.dist-info/METADATA
bgutil_ytdlp_pot_provider-1.2.2.dist-info/WHEEL
bgutil_ytdlp_pot_provider-1.2.2.dist-info/RECORD
