Metadata-Version: 2.4
Name: bgutil-ytdlp-pot-provider
Version: 1.2.2
Maintainer: grqz
Maintainer-email: Brainicism <brainicism@gmail.com>
Keywords: yt-dlp,yt-dlp-plugin,yt-dlp-pot-provider
Classifier: License :: OSI Approved :: GNU General Public License v3 (GPLv3)
Requires-Python: >=3.8
